rename_guru/__init__.py
rename_guru/__main__.py
rename_guru/process.py
rename_guru-0.0.8.dist-info/METADATA
rename_guru-0.0.8.dist-info/RECORD
rename_guru-0.0.8.dist-info/WHEEL
rename_guru-0.0.8.dist-info/top_level.txt
tests/BasicTest.py
tests/__init__.py
tests/utils.py
