Metadata-Version: 2.1
Name: rename-guru
Version: 0.0.8
Summary: Tool for duplicating code while substituting specified string inside the folder, respecting camelCase, UPPER_CASE etc.
Home-page: https://github.com/sitnarf/rename-guru
Author: sitnarf
Author-email: sitnarf@gmail.com
License: UNKNOWN
Platform: UNKNOWN
Classifier: Programming Language :: Python :: 3
Classifier: License :: OSI Approved :: MIT License
Classifier: Operating System :: OS Independent
